valid_dataset.py
valid_dataset-1.0.1.dist-info/METADATA
valid_dataset-1.0.1.dist-info/WHEEL
valid_dataset-1.0.1.dist-info/entry_points.txt
valid_dataset-1.0.1.dist-info/top_level.txt
valid_dataset-1.0.1.dist-info/RECORD
