Metadata-Version: 2.1
Name: valid_dataset
Version: 1.0.1
Requires-Dist: pyyaml
